efidgy/__init__.py
efidgy/exceptions.py
efidgy/tools.py
efidgy/asyncapi/__init__.py
efidgy/asyncapi/tools.py
efidgy/asyncapi/models/__init__.py
efidgy/asyncapi/models/idd_or.py
efidgy/impl/__init__.py
efidgy/impl/client.py
efidgy/impl/fields.py
efidgy/impl/model.py
efidgy/impl/routines.py
efidgy/impl/service.py
efidgy/models/__init__.py
efidgy/models/idd_or.py
tests/__init__.py
tests/test_models.py
efidgy-0.15.dist-info/LICENSE.md
efidgy-0.15.dist-info/METADATA
efidgy-0.15.dist-info/WHEEL
efidgy-0.15.dist-info/top_level.txt
efidgy-0.15.dist-info/RECORD
