Metadata-Version: 2.1
Name: efidgy
Version: 0.15
Summary: Python bindings to efidgy services.
Home-page: https://efidgy.com/
Author: Vasily Stepanov
Author-email: vasily.stepanov@efidgy.com
License: GPL3
Project-URL: Documentation, https://efidgy.com/docs
Project-URL: Source, https://github.com/efidgy/efidgy
Keywords: efidgy logistics optimization dispatcing vrp
Classifier: Development Status :: 3 - Alpha
Classifier: Framework :: AsyncIO
Classifier: Intended Audience :: Developers
Classifier: Intended Audience :: Science/Research
Classifier: License :: OSI Approved :: GNU General Public License v3 (GPLv3)
Classifier: Operating System :: OS Independent
Classifier: Topic :: Software Development :: Libraries
Requires-Python: >=3.6
License-File: LICENSE.md
